openmonkeymind/__init__.py
openmonkeymind/_base_omm_plugin.py
openmonkeymind/_baseopenmonkeymind.py
openmonkeymind/_dummymonkeymind.py
openmonkeymind/_exceptions.py
openmonkeymind/_omm_log_backend.py
openmonkeymind/_openmonkeymind.py
openmonkeymind/data/dummy-jobs.yaml
opensesame_extensions/open_monkey_mind/__init__.py
opensesame_extensions/open_monkey_mind/open_monkey_mind/__init__.py
opensesame_extensions/open_monkey_mind/open_monkey_mind/omm-entry-point.osexp
opensesame_extensions/open_monkey_mind/open_monkey_mind/omm-template.osexp
opensesame_extensions/open_monkey_mind/open_monkey_mind/open_monkey_mind.py
opensesame_extensions/open_monkey_mind/open_monkey_mind/open_monkey_mind.ui
opensesame_plugins/open_monkey_mind/__init__.py
opensesame_plugins/open_monkey_mind/omm_announce/__init__.py
opensesame_plugins/open_monkey_mind/omm_announce/omm_announce.png
opensesame_plugins/open_monkey_mind/omm_announce/omm_announce.py
opensesame_plugins/open_monkey_mind/omm_announce/omm_announce_large.png
opensesame_plugins/open_monkey_mind/omm_conditioner/__init__.py
opensesame_plugins/open_monkey_mind/omm_conditioner/conditioners/__init__.py
opensesame_plugins/open_monkey_mind/omm_conditioner/conditioners/_base_conditioner.py
opensesame_plugins/open_monkey_mind/omm_conditioner/conditioners/_dummy.py
opensesame_plugins/open_monkey_mind/omm_conditioner/conditioners/_seed_dispenser.py
opensesame_plugins/open_monkey_mind/omm_conditioner/omm_conditioner.png
opensesame_plugins/open_monkey_mind/omm_conditioner/omm_conditioner.py
opensesame_plugins/open_monkey_mind/omm_conditioner/omm_conditioner_large.png
opensesame_plugins/open_monkey_mind/omm_detect_participant/__init__.py
opensesame_plugins/open_monkey_mind/omm_detect_participant/omm_detect_participant.png
opensesame_plugins/open_monkey_mind/omm_detect_participant/omm_detect_participant.py
opensesame_plugins/open_monkey_mind/omm_detect_participant/omm_detect_participant_large.png
opensesame_extension_omm-0.7.0.dist-info/COPYING
opensesame_extension_omm-0.7.0.dist-info/METADATA
opensesame_extension_omm-0.7.0.dist-info/WHEEL
opensesame_extension_omm-0.7.0.dist-info/RECORD
