Metadata-Version: 2.3
Name: opensesame-extension-omm
Version: 0.7.0
Summary: OpenMonkeyMind plugins and extension for OpenSesame
License: COPYING
Author: Sebastiaan Mathôt
Author-email: s.mathot@cogsci.nl
Classifier: License :: Other/Proprietary License
Classifier: Programming Language :: Python :: 2
Classifier: Programming Language :: Python :: 2.7
Classifier: Programming Language :: Python :: 3
Classifier: Programming Language :: Python :: 3.4
Classifier: Programming Language :: Python :: 3.5
Classifier: Programming Language :: Python :: 3.6
Classifier: Programming Language :: Python :: 3.7
Classifier: Programming Language :: Python :: 3.8
Classifier: Programming Language :: Python :: 3.9
Classifier: Programming Language :: Python :: 3.10
Classifier: Programming Language :: Python :: 3.11
Classifier: Programming Language :: Python :: 3.12
Classifier: Programming Language :: Python :: 3.13
Requires-Dist: requests
Project-URL: Homepage, https://github.com/open-cogsci/omm-client
Project-URL: Repository, https://github.com/open-cogsci/omm-client
